{
  "title": "Algeria by Motorcycle",
  "date": "2026-10-01",
  "duration": 15,
  "image": "assets/upcomingTrips_img/screenshot20250925084730.jpg",
  "route": [
    "border gate.El Oued Alg. Tozeur Tns ",
    "Touggourt ",
    "Ouargla. Hassi Messaoud ",
    "Hassi Balqabour ",
    "Ain Amenas ",
    "Illizi ",
    "Ihrir Oases ",
    "Djanit "
  ],
  "pricePerDay": 110,
  "inclusions": [
    "14 notti in camera doppia in hotel 3/4/5* o migliori in loco",
    "Le colazioni e cene come da programma",
    "Guida locale su mezzo di supporto",
    "Our agency handles visa applications. ",
    "Motorcycle insurance policy ",
    "Payment of museum dues "
  ],
  "excludes": [
    "Visa fee. Payable at the customs office. ",
    "benzene "
  ],
  "itinerary": [
    {},
    {},
    {},
    {},
    {},
    {},
    {},
    {},
    {},
    {},
    {},
    {},
    {},
    {},
    {}
  ],
  "description": "<p>An original motorcycle journey to discover Algeria, through oases, desert, and breathtaking natural scenery.</p><p>An adventure steeped in majestic landscapes, ancient cities, and an authentic and vibrant culture. Crossing this vast North African country on two wheels means enjoying a unique experience, amidst fascinating roads, genuine encounters, and ever-changing panoramas.</p><p><br></p><p><strong>Entry through the border gate between Tunisia and Algeria. </strong></p><p><br></p><p>An itinerary designed to discover Algeria in all its diversity: from the desert regions on the edge of the Saharan Atlas to the immense expanses of sand and dunes over 100 meters high.</p><p></p><p><br></p><p><br></p><p></p><p></p>"
}